[{"userProfilePK":5327642,"calendarDate":"2024-11-23","deviceId":3412885051,"updateTimestamp":"2024-11-23T09:31:35.0","sport":"RUNNING","subSport":"GENERIC","vo2MaxValue":50.0,"maxMet":14.329727172851562,"maxMetCategory":"GENERIC","calibratedData":1},{"userProfilePK":5327642,"calendarDate":"2024-11-25","deviceId":3412885051,"updateTimestamp":"2024-11-25T17:12:40.0","sport":"RUNNING","subSport":"GENERIC","vo2MaxValue":50.0,"maxMet":14.32135009765625,"maxMetCategory":"GENERIC","calibratedData":1},{"userProfilePK":5327642,"calendarDate":"2024-11-29","deviceId":3412885051,"updateTimestamp":"2024-11-29T08:44:10.0","sport":"RUNNING","subSport":"GENERIC","vo2MaxValue":50.0,"maxMet":14.38043212890625,"maxMetCategory":"GENERIC","calibratedData":1},{"userProfilePK":5327642,"calendarDate":"2024-11-30","deviceId":3412885051,"updateTimestamp":"2024-11-30T09:44:06.0","sport":"RUNNING","subSport":"GENERIC","vo2MaxValue":50.0,"maxMet":14.382705688476562,"maxMetCategory":"GENERIC","calibratedData":1},{"userProfilePK":5327642,"calendarDate":"2024-12-01","deviceId":3412885051,"updateTimestamp":"2024-12-01T09:35:51.0","sport":"RUNNING","subSport":"GENERIC","vo2MaxValue":50.0,"maxMet":14.3787841796875,"maxMetCategory":"GENERIC","calibratedData":1},{"userProfilePK":5327642,"calendarDate":"2024-12-03","deviceId":3412885051,"updateTimestamp":"2024-12-03T17:29:00.0","sport":"RUNNING","subSport":"GENERIC","vo2MaxValue":50.0,"maxMet":14.359619140625,"maxMetCategory":"GENERIC","calibratedData":1},{"userProfilePK":5327642,"calendarDate":"2024-12-04","deviceId":3412885051,"updateTimestamp":"2024-12-04T20:17:04.0","sport":"RUNNING","subSport":"GENERIC","vo2MaxValue":50.0,"maxMet":14.338211059570312,"maxMetCategory":"GENERIC","calibratedData":1},{"userProfilePK":5327642,"calendarDate":"2024-12-05","deviceId":3412885051,"updateTimestamp":"2024-12-05T13:14:18.0","sport":"RUNNING","subSport":"GENERIC","vo2MaxValue":50.0,"maxMet":14.321243286132812,"maxMetCategory":"GENERIC","calibratedData":1},{"userProfilePK":5327642,"calendarDate":"2024-12-06","deviceId":3412885051,"updateTimestamp":"2024-12-06T09:22:11.0","sport":"RUNNING","subSport":"GENERIC","vo2MaxValue":50.0,"maxMet":14.319961547851562,"maxMetCategory":"GENERIC","calibratedData":1},{"userProfilePK":5327642,"calendarDate":"2024-12-07","deviceId":3412885051,"updateTimestamp":"2024-12-07T10:30:55.0","sport":"RUNNING","subSport":"GENERIC","vo2MaxValue":50.0,"maxMet":14.352462768554688,"maxMetCategory":"GENERIC","calibratedData":1},{"userProfilePK":5327642,"calendarDate":"2024-12-08","deviceId":3412885051,"updateTimestamp":"2024-12-08T09:34:30.0","sport":"RUNNING","subSport":"GENERIC","vo2MaxValue":50.0,"maxMet":14.342330932617188,"maxMetCategory":"GENERIC","calibratedData":1},{"userProfilePK":5327642,"calendarDate":"2024-12-10","deviceId":3412885051,"updateTimestamp":"2024-12-10T14:31:36.0","sport":"RUNNING","subSport":"GENERIC","vo2MaxValue":50.0,"maxMet":14.340789794921875,"maxMetCategory":"GENERIC","calibratedData":1},{"userProfilePK":5327642,"calendarDate":"2024-12-11","deviceId":3412885051,"updateTimestamp":"2024-12-11T15:53:36.0","sport":"RUNNING","subSport":"GENERIC","vo2MaxValue":50.0,"maxMet":14.343658447265625,"maxMetCategory":"GENERIC","calibratedData":1},{"userProfilePK":5327642,"calendarDate":"2024-12-12","deviceId":3412885051,"updateTimestamp":"2024-12-12T16:54:53.0","sport":"RUNNING","subSport":"GENERIC","vo2MaxValue":50.0,"maxMet":14.355926513671875,"maxMetCategory":"GENERIC","calibratedData":1},{"userProfilePK":5327642,"calendarDate":"2024-12-13","deviceId":3412885051,"updateTimestamp":"2024-12-13T12:55:17.0","sport":"RUNNING","subSport":"GENERIC","vo2MaxValue":50.0,"maxMet":14.383682250976562,"maxMetCategory":"GENERIC","calibratedData":1},{"userProfilePK":5327642,"calendarDate":"2024-12-14","deviceId":3412885051,"updateTimestamp":"2024-12-14T15:45:07.0","sport":"RUNNING","subSport":"GENERIC","vo2MaxValue":50.0,"maxMet":14.37677001953125,"maxMetCategory":"GENERIC","calibratedData":1},{"userProfilePK":5327642,"calendarDate":"2024-12-15","deviceId":3412885051,"updateTimestamp":"2024-12-15T13:02:25.0","sport":"RUNNING","subSport":"GENERIC","vo2MaxValue":50.0,"maxMet":14.379959106445312,"maxMetCategory":"GENERIC","calibratedData":1},{"userProfilePK":5327642,"calendarDate":"2024-12-16","deviceId":3412885051,"updateTimestamp":"2024-12-16T18:02:49.0","sport":"RUNNING","subSport":"GENERIC","vo2MaxValue":50.0,"maxMet":14.37762451171875,"maxMetCategory":"GENERIC","calibratedData":1},{"userProfilePK":5327642,"calendarDate":"2024-12-17","deviceId":3412885051,"updateTimestamp":"2024-12-17T17:37:57.0","sport":"RUNNING","subSport":"GENERIC","vo2MaxValue":50.0,"maxMet":14.369857788085938,"maxMetCategory":"GENERIC","calibratedData":1},{"userProfilePK":5327642,"calendarDate":"2024-12-18","deviceId":3412885051,"updateTimestamp":"2024-12-18T18:58:50.0","sport":"RUNNING","subSport":"GENERIC","vo2MaxValue":50.0,"maxMet":14.365310668945312,"maxMetCategory":"GENERIC","calibratedData":1},{"userProfilePK":5327642,"calendarDate":"2024-12-19","deviceId":3412885051,"updateTimestamp":"2024-12-19T14:41:16.0","sport":"RUNNING","subSport":"GENERIC","vo2MaxValue":50.0,"maxMet":14.370071411132812,"maxMetCategory":"GENERIC","calibratedData":1},{"userProfilePK":5327642,"calendarDate":"2024-12-20","deviceId":3412885051,"updateTimestamp":"2024-12-20T19:32:39.0","sport":"RUNNING","subSport":"GENERIC","vo2MaxValue":50.0,"maxMet":14.378814697265625,"maxMetCategory":"GENERIC","calibratedData":1},{"userProfilePK":5327642,"calendarDate":"2024-12-21","deviceId":3412885051,"updateTimestamp":"2024-12-21T13:22:58.0","sport":"RUNNING","subSport":"GENERIC","vo2MaxValue":50.0,"maxMet":14.368026733398438,"maxMetCategory":"GENERIC","calibratedData":1},{"userProfilePK":5327642,"calendarDate":"2024-12-22","deviceId":3412885051,"updateTimestamp":"2024-12-22T09:20:57.0","sport":"RUNNING","subSport":"GENERIC","vo2MaxValue":50.0,"maxMet":14.387222290039062,"maxMetCategory":"GENERIC","calibratedData":1},{"userProfilePK":5327642,"calendarDate":"2024-12-23","deviceId":3412885051,"updateTimestamp":"2024-12-23T17:29:36.0","sport":"RUNNING","subSport":"GENERIC","vo2MaxValue":50.0,"maxMet":14.391693115234375,"maxMetCategory":"GENERIC","calibratedData":1},{"userProfilePK":5327642,"calendarDate":"2024-12-24","deviceId":3412885051,"updateTimestamp":"2024-12-24T12:57:29.0","sport":"RUNNING","subSport":"GENERIC","vo2MaxValue":50.0,"maxMet":14.398300170898438,"maxMetCategory":"GENERIC","calibratedData":1},{"userProfilePK":5327642,"calendarDate":"2024-12-25","deviceId":3412885051,"updateTimestamp":"2024-12-25T09:05:21.0","sport":"RUNNING","subSport":"GENERIC","vo2MaxValue":50.0,"maxMet":14.402603149414062,"maxMetCategory":"GENERIC","calibratedData":1},{"userProfilePK":5327642,"calendarDate":"2024-12-28","deviceId":3412885051,"updateTimestamp":"2024-12-28T12:16:26.0","sport":"RUNNING","subSport":"GENERIC","vo2MaxValue":50.0,"maxMet":14.3834228515625,"maxMetCategory":"GENERIC","calibratedData":1},{"userProfilePK":5327642,"calendarDate":"2025-01-02","deviceId":3412885051,"updateTimestamp":"2025-01-02T16:28:16.0","sport":"RUNNING","subSport":"GENERIC","vo2MaxValue":50.0,"maxMet":14.375167846679688,"maxMetCategory":"GENERIC","calibratedData":1},{"userProfilePK":5327642,"calendarDate":"2025-01-05","deviceId":3412885051,"updateTimestamp":"2025-01-05T12:09:47.0","sport":"RUNNING","subSport":"GENERIC","vo2MaxValue":50.0,"maxMet":14.383285522460938,"maxMetCategory":"GENERIC","calibratedData":1},{"userProfilePK":5327642,"calendarDate":"2025-01-09","deviceId":3412885051,"updateTimestamp":"2025-01-09T13:01:45.0","sport":"RUNNING","subSport":"GENERIC","vo2MaxValue":50.0,"maxMet":14.383148193359375,"maxMetCategory":"GENERIC","calibratedData":1},{"userProfilePK":5327642,"calendarDate":"2025-01-12","deviceId":3412885051,"updateTimestamp":"2025-01-12T16:11:33.0","sport":"RUNNING","subSport":"GENERIC","vo2MaxValue":50.0,"maxMet":14.39556884765625,"maxMetCategory":"GENERIC","calibratedData":1},{"userProfilePK":5327642,"calendarDate":"2025-01-19","deviceId":3412885051,"updateTimestamp":"2025-01-19T09:44:56.0","sport":"RUNNING","subSport":"GENERIC","vo2MaxValue":50.0,"maxMet":14.41876220703125,"maxMetCategory":"GENERIC","calibratedData":1},{"userProfilePK":5327642,"calendarDate":"2025-01-22","deviceId":3412885051,"updateTimestamp":"2025-01-22T16:07:00.0","sport":"RUNNING","subSport":"GENERIC","vo2MaxValue":50.0,"maxMet":14.394317626953125,"maxMetCategory":"GENERIC","calibratedData":1},{"userProfilePK":5327642,"calendarDate":"2025-01-26","deviceId":3412885051,"updateTimestamp":"2025-01-26T11:47:42.0","sport":"RUNNING","subSport":"GENERIC","vo2MaxValue":50.0,"maxMet":14.382247924804688,"maxMetCategory":"GENERIC","calibratedData":1},{"userProfilePK":5327642,"calendarDate":"2025-01-29","deviceId":3412885051,"updateTimestamp":"2025-01-29T16:46:40.0","sport":"RUNNING","subSport":"GENERIC","vo2MaxValue":50.0,"maxMet":14.3880615234375,"maxMetCategory":"GENERIC","calibratedData":1},{"userProfilePK":5327642,"calendarDate":"2025-02-02","deviceId":3412885051,"updateTimestamp":"2025-02-02T10:45:22.0","sport":"RUNNING","subSport":"GENERIC","vo2MaxValue":50.0,"maxMet":14.350784301757812,"maxMetCategory":"GENERIC","calibratedData":1},{"userProfilePK":5327642,"calendarDate":"2025-02-09","deviceId":3412885051,"updateTimestamp":"2025-02-09T12:01:34.0","sport":"RUNNING","subSport":"GENERIC","vo2MaxValue":50.0,"maxMet":14.28363037109375,"maxMetCategory":"GENERIC","calibratedData":1},{"userProfilePK":5327642,"calendarDate":"2025-02-12","deviceId":3412885051,"updateTimestamp":"2025-02-12T14:03:56.0","sport":"RUNNING","subSport":"GENERIC","vo2MaxValue":50.0,"maxMet":14.364120483398438,"maxMetCategory":"GENERIC","calibratedData":1},{"userProfilePK":5327642,"calendarDate":"2025-02-15","deviceId":3412885051,"updateTimestamp":"2025-02-15T15:05:35.0","sport":"RUNNING","subSport":"GENERIC","vo2MaxValue":50.0,"maxMet":14.325271606445312,"maxMetCategory":"GENERIC","calibratedData":1},{"userProfilePK":5327642,"calendarDate":"2025-02-22","deviceId":3412885051,"updateTimestamp":"2025-02-22T08:55:47.0","sport":"RUNNING","subSport":"GENERIC","vo2MaxValue":50.0,"maxMet":14.323974609375,"maxMetCategory":"GENERIC","calibratedData":1},{"userProfilePK":5327642,"calendarDate":"2025-02-22","deviceId":3412885051,"updateTimestamp":"2025-02-22T09:28:20.0","sport":"RUNNING","subSport":"GENERIC","vo2MaxValue":50.0,"maxMet":14.323974609375,"maxMetCategory":"GENERIC","calibratedData":1},{"userProfilePK":5327642,"calendarDate":"2025-02-22","deviceId":3412885051,"updateTimestamp":"2025-02-22T09:38:11.0","sport":"RUNNING","subSport":"GENERIC","vo2MaxValue":50.0,"maxMet":14.323974609375,"maxMetCategory":"GENERIC","calibratedData":1}]